tests/__init__.py
tests/test_clients.py
tests/test_exceptions.py
tests/test_forces.py
tests/test_neighbourhoods.py
tests/test_stop_search.py
tests/test_street_level.py
tests/test_utils.py
uk_police/__init__.py
uk_police/client.py
uk_police/exceptions.py
uk_police/forces.py
uk_police/neighbourhoods.py
uk_police/stop_search.py
uk_police/street_level.py
uk_police/utils.py
uk_police-0.3.0.dist-info/LICENSE
uk_police-0.3.0.dist-info/METADATA
uk_police-0.3.0.dist-info/WHEEL
uk_police-0.3.0.dist-info/top_level.txt
uk_police-0.3.0.dist-info/RECORD
