Metadata-Version: 2.2
Name: uk_police
Version: 0.3.0
Summary: A Python wrapper for the UK Police API.
Home-page: https://github.com/Chaaronn/UK_Police_API
Author: Matt Voce
Author-email: mattvoce7259@gmail.com
Classifier: Programming Language :: Python :: 3
Classifier: License :: OSI Approved :: MIT License
Classifier: Operating System :: OS Independent
Requires-Python: >=3.7
License-File: LICENSE
Requires-Dist: requests>=2.25.0
Dynamic: author
Dynamic: author-email
Dynamic: classifier
Dynamic: description
Dynamic: description-content-type
Dynamic: home-page
Dynamic: requires-dist
Dynamic: requires-python
Dynamic: summary
